clsquery/__init__.py
clsquery/cli.py
clsquery/constants.py
clsquery/convert_classes_to_table.py
clsquery/custom_logger.py
clsquery/default_formatter.py
clsquery/filter_by_types.py
clsquery/format_list.py
clsquery/format_table.py
clsquery/get_classes_at_path.py
clsquery/get_classes_from_paths.py
clsquery/get_time.py
clsquery/has_supertype.py
clsquery/query.py
clsquery/classes/class_query.py
clsquery/classes/class_query_formatter.py
clsquery/classes/class_query_item.py
clsquery/classes/class_query_results.py
clsquery-1.2.dist-info/LICENSE
clsquery-1.2.dist-info/METADATA
clsquery-1.2.dist-info/WHEEL
clsquery-1.2.dist-info/top_level.txt
clsquery-1.2.dist-info/RECORD
