Metadata-Version: 2.1
Name: clsquery
Version: 1.2
Summary: A package for querying Python classes
Author-email: Kenneth Mead <kennethmead784@gmail.com>
Project-URL: Homepage, https://github.com/Xerner/python-class-query
Classifier: Programming Language :: Python :: 3
Classifier: Environment :: Console
Classifier: Intended Audience :: Developers
Classifier: License :: OSI Approved :: MIT License
Classifier: Operating System :: Microsoft :: Windows
Classifier: Operating System :: POSIX
Classifier: Programming Language :: Python
Requires-Python: >=3.7
License-File: LICENSE
Requires-Dist: pytz
